cstq/__init__.py
cstq/__version__.py
cstq/constants.py
cstq/csttraformers.py
cstq/cstvisitors.py
cstq/matchers.py
cstq/matchers_helpers.py
cstq/node2id.py
cstq/obj2cst.py
cstq/obj2x.py
cstq/query.py
cstq/nodes/__init__.py
cstq/nodes/call.py
cstq/nodes/class_def.py
cstq/nodes/extended.py
cstq/nodes/range.py
cstq/nodes/sequence.py
cstq-0.0.20.dist-info/METADATA
cstq-0.0.20.dist-info/WHEEL
cstq-0.0.20.dist-info/licenses/LICENSE.txt
cstq-0.0.20.dist-info/RECORD
