Metadata-Version: 2.3
Name: cstq
Version: 0.0.20
Project-URL: Documentation, https://github.com/aleivag/cstq#readme
Project-URL: Issues, https://github.com/aleivag/cstq/issues
Project-URL: Source, https://github.com/aleivag/cstq
Author-email: Alvaro Leiva <aleivag@gmail.com>
License: MIT License
License-File: LICENSE.txt
Classifier: Development Status :: 4 - Beta
Classifier: License :: OSI Approved :: MIT License
Classifier: Programming Language :: Python
Classifier: Programming Language :: Python :: 3.10
Classifier: Programming Language :: Python :: 3.11
Classifier: Programming Language :: Python :: Implementation :: CPython
Classifier: Programming Language :: Python :: Implementation :: PyPy
Requires-Python: >=3.10
Requires-Dist: libcst
